libmodel/__init__.py
libmodel/django.py
libmodel/utils.py
libmodel-0.0.6.dist-info/LICENSE
libmodel-0.0.6.dist-info/METADATA
libmodel-0.0.6.dist-info/WHEEL
libmodel-0.0.6.dist-info/top_level.txt
libmodel-0.0.6.dist-info/RECORD
